{
  "site": {
    "name": "Mine de Démonstration - Kinshasa",
    "centerLat": -4.4195401,
    "centerLng": 15.3097856,
    "minLat": -4.421,
    "maxLat": -4.418,
    "minLng": 15.308,
    "maxLng": 15.3115
  },
  "zones": [
    {
      "name": "Entrée principale",
      "color": "#f97316",
      "points": [
        {
          "lat": -4.41854,
          "lng": 15.308786
        },
        {
          "lat": -4.41854,
          "lng": 15.310786
        },
        {
          "lat": -4.42054,
          "lng": 15.310786
        },
        {
          "lat": -4.42054,
          "lng": 15.308786
        }
      ]
    },
    {
      "name": "Zone d'extraction",
      "color": "#3b82f6",
      "points": [
        {
          "lat": -4.648001,
          "lng": 27.477
        },
        {
          "lat": -4.643,
          "lng": 27.477
        },
        {
          "lat": -4.643,
          "lng": 27.483
        },
        {
          "lat": -4.648,
          "lng": 27.483
        }
      ]
    },
    {
      "name": "Zone de traitement",
      "color": "#08e258",
      "points": [
        {
          "lat": -4.4194,
          "lng": 15.31
        },
        {
          "lat": -4.4194,
          "lng": 15.3113
        },
        {
          "lat": -4.4205,
          "lng": 15.3113
        },
        {
          "lat": -4.4205,
          "lng": 15.31
        }
      ]
    }
  ]
}